{
  "series_title": "כָּכָה זֶה בְּעִבְרִית!",
  "quiz_number": 1,
  "quiz_title": "חידון לשון 1",
  "questions": [
    {
      "question": "באיזה מהטקסטים הכתיב תקני?",
      "answers": [
        { "text": "פריסת הכוחות האמריקניים באיזור", "correct": false },
        { "text": "פריסת הכוחות האמריקנים באזור", "correct": false },
        { "text": "פריסת הכוחות האמריקניים באזור", "correct": true },
        { "text": "פריסת הכוחות האמריקנים באיזור", "correct": false }
      ],
      "explanation": "רק כשמדובר בבני אדם, יש לכתוב ביו\"ד אחת: **האמריקנים**."
    },
    {
      "question": "בַּחֲרוּ את הנוסח שאינו שגוי:",
      "answers": [
        { "text": "בתגובה להודעת טראמפ הבהירו האמירתים...", "correct": false },
        { "text": "בתגובה על הודעת טראמפ הבהירו האמירותים...", "correct": true },
        { "text": "בתגובה להודעת טראמפ הבהירו האמירותים...", "correct": false }
      ],
      "explanation": "**מגיבים** למישהו **על** משהו.\nאנשי האֵמירוּיות הם אֵמירוּתים."
    },
    {
      "question": "איך יש להגות?",
      "answers": [
        { "text": "מאחורי סורֵג וּבְֿריח", "correct": true },
        { "text": "מאחורי סורָג וּבְֿריח", "correct": true },
        { "text": "מאחורי סורָג וּבָֿריח", "correct": false },
        { "text": "מאחורי סורָג וּבָּריח", "correct": false }
      ],
      "explanation": "מותר לומר גם **סוֹרָג** וגם **סוֹרֵג**.\nהֶתקן הנעילה נקרא **בְּרִיחַ**."
    },
    {
      "question": "מהי ההגייה התקנית של **דלפק**?",
      "answers": [
        { "text": "דַלפָּק", "correct": false },
        { "text": "דַלפֵּק", "correct": false },
        { "text": "דֶלפֵּק", "correct": true },
        { "text": "דֶלפַּק", "correct": false }
      ],
      "explanation": "למה? ככה! מקור המילה כנראה מיוונית."
    },
    {
      "question": "איך ראוי לומר את התאריך **ב־6.6**?",
      "answers": [
        { "text": "בַּשישי לַשישי", "correct": false },
        { "text": "בְּשישה ביוני", "correct": true },
        { "text": "בַּשישה ביוני", "correct": false },
        { "text": "בְּשישה ליוני", "correct": false }
      ],
      "explanation": "אין לתת ה\"א הידיעה בתאריכים,\nואות היחס לפני שם החודש היא בי\"ת."
    }
  ]
}
